odoo/addons/shopfloor_reception_packaging_dimension_mobile/README.rst
odoo/addons/shopfloor_reception_packaging_dimension_mobile/__init__.py
odoo/addons/shopfloor_reception_packaging_dimension_mobile/__manifest__.py
odoo/addons/shopfloor_reception_packaging_dimension_mobile/i18n/it.po
odoo/addons/shopfloor_reception_packaging_dimension_mobile/i18n/shopfloor_reception_packaging_dimension_mobile.pot
odoo/addons/shopfloor_reception_packaging_dimension_mobile/readme/CONTRIBUTORS.md
odoo/addons/shopfloor_reception_packaging_dimension_mobile/readme/DESCRIPTION.md
odoo/addons/shopfloor_reception_packaging_dimension_mobile/static/description/icon.png
odoo/addons/shopfloor_reception_packaging_dimension_mobile/static/description/index.html
odoo/addons/shopfloor_reception_packaging_dimension_mobile/static/src/demo/demo.reception.pkg.dimension.esm.js
odoo/addons/shopfloor_reception_packaging_dimension_mobile/static/src/scenario/reception_packaging_dimension.esm.js
odoo/addons/shopfloor_reception_packaging_dimension_mobile/templates/assets.xml
odoo_addon_shopfloor_reception_packaging_dimension_mobile-18.0.1.0.1.dist-info/METADATA
odoo_addon_shopfloor_reception_packaging_dimension_mobile-18.0.1.0.1.dist-info/WHEEL
odoo_addon_shopfloor_reception_packaging_dimension_mobile-18.0.1.0.1.dist-info/top_level.txt
odoo_addon_shopfloor_reception_packaging_dimension_mobile-18.0.1.0.1.dist-info/RECORD
